{
    "pairs.enableCharacters": ["(", "[", "{", "'", "\"", "`"],
    "tsserver.log": "verbose",
    "tsserver.trace.server": "verbose",
    "suggest.maxCompleteItemCount": 20,
    "coc.preferences.formatOnSave": false,
    // "coc.preferences.formatOnSaveFiletypes": [
    //     "javascript",
    //     "typescript",
    //     "typescriptreact",
    //     "json",
    //     "javascriptreact",
    //     "typescript.tsx"
    // ],
    "diagnostic.errorSign": "•",
    "prettier.tabWidth": 4,
    "eslint.enable": true,
    "prettier.singleQuote": true,
    "prettier.trailingComma": "es5"
}
